pic2stl/__init__.py
pic2stl/pic2stl.py
pic2stl-10.0.12.dist-info/METADATA
pic2stl-10.0.12.dist-info/WHEEL
pic2stl-10.0.12.dist-info/licenses/LICENSE
pic2stl-10.0.12.dist-info/RECORD
