Metadata-Version: 2.4
Name: pic2stl
Version: 10.0.12
Summary: img2stl is a Python package that converts an image to a 3D STL models.
Project-URL: Homepage, https://github.com/niljub/pic2stl/
Project-URL: Issues, https://github.com/niljub/pic2stl/issues
Author-email: niljub <dickergamer@tutanota.com>
License-File: LICENSE
Classifier: License :: OSI Approved :: MIT License
Classifier: Operating System :: OS Independent
Classifier: Programming Language :: Python :: 3
Requires-Python: >=3.9
Requires-Dist: cairosvg>=2.5.2
Requires-Dist: numpy-stl==3.1.1
Requires-Dist: numpy==1.26.4
Requires-Dist: pillow==10.3.0
Requires-Dist: python-utils==3.8.2
Requires-Dist: scipy==1.13.0
Requires-Dist: trimesh==4.3.2
Requires-Dist: typing-extensions==4.11.0
